rehull/__init__.py
rehull-0.1.dist-info/LICENSE
rehull-0.1.dist-info/WHEEL
rehull-0.1.dist-info/METADATA
rehull-0.1.dist-info/RECORD
