Metadata-Version: 2.1
Name: rehull
Version: 0.1
Summary: stub
Author-email: rehull <rehull@sent.com>
Classifier: License :: OSI Approved :: GNU General Public License v3 or later (GPLv3+)
Project-URL: Home, https://rehull.com
